byted_overpass_tiktok_search_trending_mining_data_center/__init__.py
byted_overpass_tiktok_search_trending_mining_data_center-0.0.1.dist-info/METADATA
byted_overpass_tiktok_search_trending_mining_data_center-0.0.1.dist-info/WHEEL
byted_overpass_tiktok_search_trending_mining_data_center-0.0.1.dist-info/top_level.txt
byted_overpass_tiktok_search_trending_mining_data_center-0.0.1.dist-info/RECORD
