Metadata-Version: 2.1
Name: byted-overpass-tiktok-search-trending-mining-data-center
Version: 0.0.1
Summary: A simple package named byted_overpass_tiktok_search_trending_mining_data_center
Home-page: https://github.com/artifact/byted_overpass_tiktok_search_trending_mining_data_center.git
Author: artifact
Author-email: artifact@example.com
License: UNKNOWN
Platform: UNKNOWN
Classifier: Programming Language :: Python :: 3
Classifier: License :: OSI Approved :: MIT License
Classifier: Operating System :: OS Independent
